LICENSE
spotipy/__init__.py
spotipy/client.py
spotipy/exceptions.py
spotipy/http.py
spotipy/objects/__init__.py
spotipy/objects/actions.py
spotipy/objects/album.py
spotipy/objects/artist.py
spotipy/objects/base.py
spotipy/objects/category.py
spotipy/objects/copyright.py
spotipy/objects/device.py
spotipy/objects/enums.py
spotipy/objects/episode.py
spotipy/objects/followers.py
spotipy/objects/image.py
spotipy/objects/playback.py
spotipy/objects/playlist.py
spotipy/objects/recommendation.py
spotipy/objects/search.py
spotipy/objects/show.py
spotipy/objects/token.py
spotipy/objects/track.py
spotipy/objects/user.py
spotipy/py.typed
spotipy/typings/__init__.py
spotipy/typings/objects.py
spotipy/utils.py
spotipy/values.py
spoti.py-0.1.3.dist-info/LICENSE
spoti.py-0.1.3.dist-info/WHEEL
spoti.py-0.1.3.dist-info/METADATA
spoti.py-0.1.3.dist-info/RECORD
